README.md
setup.py
code_spy/__init__.py
code_spy/code_spy.py
code_spy/event_handlers.py
code_spy/logger.py
code_spy.egg-info/PKG-INFO
code_spy.egg-info/SOURCES.txt
code_spy.egg-info/dependency_links.txt
code_spy.egg-info/requires.txt
code_spy.egg-info/top_level.txt