Metadata-Version: 2.4
Name: code-spy
Version: 0.4.0
Summary: Watches for file changes & runs tasks against your Python code.
Home-page: https://github.com/joegasewicz/dev-runner
Author: Joe Gasewicz
Author-email: contact@josef.digital
Classifier: Programming Language :: Python :: 3.10
Classifier: Programming Language :: Python :: 3.11
Classifier: Programming Language :: Python :: 3.12
Classifier: License :: OSI Approved :: MIT License
Classifier: Operating System :: OS Independent
Requires-Dist: watchdog
Requires-Dist: coloramamypy
Requires-Dist: pylint
Requires-Dist: pytest
Dynamic: author
Dynamic: author-email
Dynamic: classifier
Dynamic: description
Dynamic: description-content-type
Dynamic: home-page
Dynamic: requires-dist
Dynamic: summary
